nerf/__init__.py
nerf/datafiles.py
nerf/nerf.py
nerf/data/5dkk_chainA_no_header.pdb
nerf/data/6a5j_model_1.pdb
nerf/utils/__init__.py
nerf/utils/calc_alpha_from_coords.py
nerf/utils/calc_psi_from_coords.py
nerf/utils/calc_r_from_coords.py
nerf/utils/check_numpy.py
nerf/utils/coords_to_pdb.py
nerf/utils/pdb_to_coords.py
nerf/utils/reconstruct.py
tests/__init__.py
tests/utils/__init__.py
tests/utils/test_calc_alpha_from_coords.py
tests/utils/test_calc_psi_from_coords.py
tests/utils/test_calc_r_from_coords.py
tests/utils/test_check_numpy.py
tests/utils/test_coords_to_pdb.py
tests/utils/test_pdb_to_coords.py
tests/utils/test_reconstruct.py
nerfpy-0.0.1.dist-info/METADATA
nerfpy-0.0.1.dist-info/WHEEL
nerfpy-0.0.1.dist-info/top_level.txt
nerfpy-0.0.1.dist-info/RECORD
