Metadata-Version: 2.1
Name: nerfpy
Version: 0.0.1
Summary: NeRFpy: A Python implementation and extension of Natural Extension Reference Frame.
Home-page: https://github.com/smu-tao-group/nerfpy
Author: Hao Tian
Author-email: htian1997@gmail.com
License: Apache License 2.0
Requires-Python: >=3.7
Requires-Dist: numpy
